pocket_coffea/__init__.py
pocket_coffea/__main__.py
pocket_coffea/__meta__.py
pocket_coffea/_version.py
pocket_coffea/_version.pyi
pocket_coffea/py.typed
pocket_coffea/executors/__init__.py
pocket_coffea/executors/executors_CLAIX.py
pocket_coffea/executors/executors_DESY_NAF.py
pocket_coffea/executors/executors_RWTH.py
pocket_coffea/executors/executors_T3_CH_PSI.py
pocket_coffea/executors/executors_base.py
pocket_coffea/executors/executors_brux.py
pocket_coffea/executors/executors_casa.py
pocket_coffea/executors/executors_cern_swan.py
pocket_coffea/executors/executors_infn_af.py
pocket_coffea/executors/executors_lxplus.py
pocket_coffea/executors/executors_manual_jobs.py
pocket_coffea/executors/executors_oscar.py
pocket_coffea/executors/executors_purdue_af.py
pocket_coffea/executors/executors_rubin.py
pocket_coffea/law_tasks/utils.py
pocket_coffea/law_tasks/configuration/general.py
pocket_coffea/law_tasks/configuration/plotting.py
pocket_coffea/law_tasks/tasks/base.py
pocket_coffea/law_tasks/tasks/datacard.py
pocket_coffea/law_tasks/tasks/datasets.py
pocket_coffea/law_tasks/tasks/plotting.py
pocket_coffea/law_tasks/tasks/runner.py
pocket_coffea/lib/__init__.py
pocket_coffea/lib/categorization.py
pocket_coffea/lib/columns_manager.py
pocket_coffea/lib/cut_definition.py
pocket_coffea/lib/cut_functions.py
pocket_coffea/lib/deltaR_matching.py
pocket_coffea/lib/gen_objects.py
pocket_coffea/lib/hist_manager.py
pocket_coffea/lib/jets.py
pocket_coffea/lib/leptons.py
pocket_coffea/lib/objects.py
pocket_coffea/lib/parton_provenance.py
pocket_coffea/lib/photon.py
pocket_coffea/lib/reconstruction.py
pocket_coffea/lib/scale_factors.py
pocket_coffea/lib/triggers.py
pocket_coffea/lib/weights/__init__.py
pocket_coffea/lib/weights/test_weights_mechanism.py
pocket_coffea/lib/weights/weights.py
pocket_coffea/lib/weights/weights_manager.py
pocket_coffea/lib/weights/common/__init__.py
pocket_coffea/lib/weights/common/common.py
pocket_coffea/lib/weights/common/weights_run2_UL.py
pocket_coffea-0.9.10.dist-info/licenses/LICENSE
pocket_coffea-0.9.10.dist-info/METADATA
pocket_coffea-0.9.10.dist-info/WHEEL
pocket_coffea-0.9.10.dist-info/entry_points.txt
pocket_coffea-0.9.10.dist-info/top_level.txt
pocket_coffea-0.9.10.dist-info/RECORD
